{"version": 0.6, "generator": "Overpass API 0.7.62.11 87bfad18", "osm3s": {"timestamp_osm_base": "2026-06-20T17:26:45Z", "copyright": "The data included in this document is from www.openstreetmap.org. The data is made available under ODbL."}, "elements": [{"type": "node", "id": 246171013, "lat": 12.9636229, "lon": 77.5851479, "tags": {"highway": "traffic_signals", "junction": "yes", "traffic_signals:countdown": "yes"}}, {"type": "node", "id": 429001262, "lat": 12.9638856, "lon": 77.585035, "tags": {"highway": "traffic_signals", "traffic_signals": "signal", "traffic_signals:countdown": "yes"}}, {"type": "node", "id": 1568922532, "lat": 12.9636018, "lon": 77.5844925, "tags": {"bus": "yes", "highway": "bus_stop", "name": "Town Hall", "name:en": "Town Hall", "name:kn": "\u0cae\u0cb9\u0cbe\u0ca8\u0c97\u0cb0 \u0caa\u0cbe\u0cb2\u0cbf\u0c95\u0cc6", "network": "BMTC", "operator": "BMTC", "public_transport": "platform"}}, {"type": "node", "id": 1739362330, "lat": 12.9639001, "lon": 77.5842677, "tags": {"bench": "yes", "bin": "yes", "bus": "yes", "check_date:bench": "2022-09-25", "covered": "yes", "highway": "bus_stop", "name": "Town Hall", "name:en": "Town Hall", "name:kn": "\u0cae\u0cb9\u0cbe\u0ca8\u0c97\u0cb0 \u0caa\u0cbe\u0cb2\u0cbf\u0c95\u0cc6", "network": "BMTC", "operator": "BMTC", "public_transport": "platform", "shelter": "yes"}}, {"type": "node", "id": 6460998310, "lat": 12.9635851, "lon": 77.5849613, "tags": {"highway": "traffic_signals", "traffic_signals": "signal", "traffic_signals:countdown": "yes"}}, {"type": "node", "id": 9952942397, "lat": 12.9639337, "lon": 77.5850123, "tags": {"highway": "crossing"}}, {"type": "node", "id": 9952942400, "lat": 12.9639528, "lon": 77.5839952, "tags": {"crossing": "marked", "crossing:markings": "yes", "highway": "crossing"}}, {"type": "node", "id": 10016370962, "lat": 12.9636101, "lon": 77.584957, "tags": {"crossing": "traffic_signals", "crossing:markings": "zebra", "highway": "crossing", "traffic_signals:countdown": "yes"}}, {"type": "node", "id": 11459019883, "lat": 12.9636463, "lon": 77.5851569, "tags": {"crossing": "traffic_signals", "crossing:markings": "zebra", "highway": "crossing", "traffic_signals:countdown": "yes"}}, {"type": "node", "id": 12137671787, "lat": 12.9639243, "lon": 77.5846015, "tags": {"highway": "crossing"}}, {"type": "node", "id": 12139050231, "lat": 12.9637859, "lon": 77.585055, "tags": {"crossing": "traffic_signals", "highway": "crossing"}}, {"type": "node", "id": 12139050232, "lat": 12.9638877, "lon": 77.5850464, "tags": {"crossing": "traffic_signals", "highway": "crossing"}}, {"type": "node", "id": 12139050240, "lat": 12.9631696, "lon": 77.5847342, "tags": {"crossing": "unmarked", "crossing:markings": "no", "highway": "crossing"}}, {"type": "node", "id": 12466444263, "lat": 12.9634848, "lon": 77.5839473, "tags": {"crossing": "unmarked", "crossing:markings": "no", "highway": "crossing"}}, {"type": "node", "id": 12466444266, "lat": 12.9634023, "lon": 77.5833463, "tags": {"crossing": "unmarked", "crossing:markings": "no", "highway": "crossing"}}]}