{"version": 0.6, "generator": "Overpass API 0.7.62.11 87bfad18", "osm3s": {"timestamp_osm_base": "2026-06-20T17:46:07Z", "copyright": "The data included in this document is from www.openstreetmap.org. The data is made available under ODbL."}, "elements": [{"type": "way", "id": 23029284, "tags": {"auto_rickshaw": "no", "highway": "secondary", "lanes": "3", "name": "Brigade Road", "name:kn": "\u0cac\u0ccd\u0cb0\u0cbf\u0c97\u0cc7\u0ca1\u0ccd \u0cb0\u0cb8\u0ccd\u0ca4\u0cc6", "oneway": "yes", "sidewalk": "separate", "smoothness": "excellent", "surface": "asphalt"}}, {"type": "way", "id": 23029716, "tags": {"highway": "primary_link", "lane_markings": "no", "oneway": "yes", "sidewalk": "separate", "surface": "asphalt"}}, {"type": "way", "id": 28126801, "tags": {"highway": "residential", "lanes": "2", "motor_vehicle": "yes", "name": "Markham Road", "name:kn": "\u0cae\u0cbe\u0cb0\u0ccd\u0c95\u0cae\u0ccd \u0cb0\u0cb8\u0ccd\u0ca4\u0cc6", "surface": "asphalt"}}, {"type": "way", "id": 57885698, "tags": {"area": "yes", "highway": "pedestrian", "name": "St. Patrick's Square", "place": "square", "smoothness": "excellent", "surface": "sett"}}, {"type": "way", "id": 172955372, "tags": {"access": "yes", "highway": "tertiary", "lane_markings": "no", "name": "Magrath Road", "name:kn": "\u0cae\u0c97\u0ccd\u0cb0\u0cbe\u0ca4\u0ccd \u0cb0\u0cb8\u0ccd\u0ca4\u0cc6", "oneway": "no", "smoothness": "excellent", "surface": "asphalt"}}, {"type": "way", "id": 328748212, "tags": {"access": "permissive", "highway": "footway", "surface": "cobblestone"}}, {"type": "way", "id": 403474595, "tags": {"access": "permissive", "highway": "service", "oneway": "yes", "service": "driveway", "surface": "cobblestone"}}, {"type": "way", "id": 403474596, "tags": {"access": "permissive", "highway": "service", "service": "driveway", "surface": "cobblestone"}}, {"type": "way", "id": 403474597, "tags": {"access": "permissive", "highway": "service", "service": "driveway", "surface": "cobblestone"}}, {"type": "way", "id": 403474598, "tags": {"access": "permissive", "highway": "service", "service": "driveway", "surface": "cobblestone"}}, {"type": "way", "id": 403474599, "tags": {"access": "permissive", "highway": "service", "service": "driveway", "surface": "cobblestone"}}, {"type": "way", "id": 461556535, "tags": {"hazard": "school_zone", "highway": "primary", "lanes": "4", "maxspeed": "25", "maxspeed:type": "sign", "name": "Residency Road", "name:kn": "\u0cb0\u0cc6\u0cb8\u0cbf\u0ca1\u0cc6\u0ca8\u0ccd\u0cb8\u0cbf \u0cb0\u0cb8\u0ccd\u0ca4\u0cc6", "official_name": "Field Marshal Cariappa Road", "official_name:etymology:wikidata": "Q3630913", "official_name:kn": "\u0c95\u0cbe\u0cb0\u0cbf\u0caf\u0caa\u0ccd\u0caa \u0cb0\u0cb8\u0ccd\u0ca4\u0cc6", "old_name": "Residency Road", "oneway": "yes", "short_name": "F M Cariappa Road", "sidewalk": "separate", "smoothness": "excellent", "surface": "asphalt", "turn:lanes": "left|through|through|through|"}}, {"type": "way", "id": 685246495, "tags": {"bicycle": "designated", "foot": "designated", "highway": "cycleway", "name": "Field Marshall Cariappa Cycle Path", "name:etymology:wikidata": "Q3630913", "segregated": "yes", "smoothness": "intermediate", "surface": "paving_stones"}}, {"type": "way", "id": 694929059, "tags": {"footway": "sidewalk", "highway": "footway", "segregated": "yes", "surface": "paving_stones"}}, {"type": "way", "id": 701072936, "tags": {"access": "permissive", "highway": "service", "service": "driveway", "surface": "cobblestone"}}, {"type": "way", "id": 701072939, "tags": {"button_operated": "no", "crossing": "traffic_signals", "crossing:island": "no", "crossing:markings": "zebra", "footway": "crossing", "highway": "footway", "surface": "asphalt", "tactile_paving": "no"}}, {"type": "way", "id": 701072941, "tags": {"button_operated": "no", "crossing": "traffic_signals", "crossing:island": "no", "crossing:markings": "zebra", "footway": "crossing", "highway": "footway", "surface": "asphalt", "tactile_paving": "no"}}, {"type": "way", "id": 701072942, "tags": {"button_operated": "no", "crossing": "traffic_signals", "crossing:island": "no", "crossing:markings": "zebra", "footway": "crossing", "highway": "footway", "surface": "asphalt", "tactile_paving": "no"}}, {"type": "way", "id": 763290547, "tags": {"highway": "primary", "maxspeed": "40", "name": "Residency Road", "name:etymology:wikidata": "Q3630913", "name:kn": "\u0cb0\u0cc6\u0cb8\u0cbf\u0ca1\u0cc6\u0ca8\u0ccd\u0cb8\u0cbf \u0cb0\u0cb8\u0ccd\u0ca4\u0cc6", "note": "Whitetopping work completed in 2025", "official_name": "Field Marshal Cariappa Road", "official_name:etymology:wikidata": "Q3630913", "official_name:kn": "\u0c95\u0cbe\u0cb0\u0cbf\u0caf\u0caa\u0ccd\u0caa \u0cb0\u0cb8\u0ccd\u0ca4\u0cc6", "old_name": "Residency Road", "oneway": "yes", "short_name": "F M Cariappa Road", "sidewalk": "separate", "smoothness": "excellent", "surface": "concrete"}}, {"type": "way", "id": 763290548, "tags": {"cycleway:right": "lane", "cycleway:right:surface": "paving_stones", "highway": "secondary", "lanes": "3", "name": "Museum Road", "name:kn": "\u0cb8\u0c82\u0c97\u0ccd\u0cb0\u0cb9\u0cbe\u0cb2\u0caf \u0cb0\u0cb8\u0ccd\u0ca4\u0cc6", "oneway": "yes", "sidewalk": "separate", "smoothness": "excellent", "surface": "asphalt"}}, {"type": "way", "id": 764406991, "tags": {"auto_rickshaw": "no", "highway": "secondary", "lanes": "3", "name": "Brigade Road", "name:kn": "\u0cac\u0ccd\u0cb0\u0cbf\u0c97\u0cc7\u0ca1\u0ccd \u0cb0\u0cb8\u0ccd\u0ca4\u0cc6", "oneway": "yes", "sidewalk": "both", "smoothness": "excellent"}}, {"type": "way", "id": 764406992, "tags": {"highway": "primary_link", "oneway": "yes", "sidewalk": "separate", "surface": "asphalt"}}, {"type": "way", "id": 766411085, "tags": {"button_operated": "no", "crossing": "traffic_signals", "crossing:markings": "zebra", "footway": "crossing", "highway": "footway", "smoothness": "good", "surface": "asphalt"}}, {"type": "way", "id": 1066870624, "tags": {"area": "yes", "area:highway": "footway", "highway": "footway", "noname": "yes", "smoothness": "good", "surface": "paving_stones"}}, {"type": "way", "id": 1087940511, "tags": {"footway": "sidewalk", "highway": "footway", "smoothness": "excellent", "surface": "paving_stones"}}, {"type": "way", "id": 1094091139, "tags": {"access": "private", "highway": "service"}}, {"type": "way", "id": 1094100944, "tags": {"highway": "service"}}, {"type": "way", "id": 1096172762, "tags": {"footway": "sidewalk", "highway": "footway", "smoothness": "excellent", "surface": "paving_stones"}}, {"type": "way", "id": 1096172763, "tags": {"footway": "sidewalk", "highway": "footway", "smoothness": "excellent"}}, {"type": "way", "id": 1096797091, "tags": {"highway": "primary", "lanes": "3", "maxspeed": "40", "name": "Residency Road", "name:etymology:wikidata": "Q3630913", "name:kn": "\u0cb0\u0cc6\u0cb8\u0cbf\u0ca1\u0cc6\u0ca8\u0ccd\u0cb8\u0cbf \u0cb0\u0cb8\u0ccd\u0ca4\u0cc6", "note": "Whitetopping work completed in 2025", "official_name": "Field Marshal Cariappa Road", "official_name:etymology:wikidata": "Q3630913", "official_name:kn": "\u0c95\u0cbe\u0cb0\u0cbf\u0caf\u0caa\u0ccd\u0caa \u0cb0\u0cb8\u0ccd\u0ca4\u0cc6", "old_name": "Residency Road", "oneway": "yes", "short_name": "F M Cariappa Road", "sidewalk": "separate", "smoothness": "excellent", "surface": "concrete"}}, {"type": "way", "id": 1106057225, "tags": {"footway": "sidewalk", "highway": "footway", "surface": "paving_stones"}}, {"type": "way", "id": 1106057226, "tags": {"button_operated": "no", "crossing": "traffic_signals", "crossing:island": "no", "crossing:markings": "zebra", "footway": "crossing", "highway": "footway", "surface": "asphalt", "tactile_paving": "no"}}, {"type": "way", "id": 1106057227, "tags": {"bicycle": "no", "footway": "sidewalk", "highway": "footway", "kerb": "raised", "surface": "paving_stones"}}, {"type": "way", "id": 1106057231, "tags": {"footway": "sidewalk", "highway": "footway", "kerb": "raised", "surface": "paving_stones"}}, {"type": "way", "id": 1124838024, "tags": {"access": "permissive", "highway": "service", "service": "driveway"}}, {"type": "way", "id": 1125692649, "tags": {"access": "private", "highway": "service"}}, {"type": "way", "id": 1125692650, "tags": {"access": "permissive", "highway": "footway", "surface": "cobblestone"}}, {"type": "way", "id": 1125692651, "tags": {"access": "permissive", "highway": "footway", "surface": "cobblestone"}}, {"type": "way", "id": 1125692653, "tags": {"highway": "footway"}}, {"type": "way", "id": 1136281758, "tags": {"highway": "residential", "lanes": "2", "name": "Rest House Road", "surface": "asphalt"}}, {"type": "way", "id": 1165356263, "tags": {"access": "private", "highway": "service"}}, {"type": "way", "id": 1183334224, "tags": {"bicycle": "designated", "highway": "cycleway", "name": "Field Marshall Cariappa Cycle Path", "name:etymology:wikidata": "Q3630913", "surface": "paving_stones", "width": "1.5"}}, {"type": "way", "id": 1183334226, "tags": {"highway": "service"}}, {"type": "way", "id": 1196481561, "tags": {"access": "permissive", "highway": "service", "service": "driveway", "surface": "cobblestone"}}, {"type": "way", "id": 1196481563, "tags": {"access": "permissive", "highway": "service"}}, {"type": "way", "id": 1210471210, "tags": {"access": "permissive", "highway": "footway"}}, {"type": "way", "id": 1217769078, "tags": {"highway": "path"}}, {"type": "way", "id": 1217769080, "tags": {"highway": "service"}}, {"type": "way", "id": 1217769081, "tags": {"footway": "sidewalk", "highway": "footway", "kerb": "raised"}}, {"type": "way", "id": 1217769082, "tags": {"footway": "sidewalk", "highway": "footway", "kerb": "raised"}}, {"type": "way", "id": 1217769083, "tags": {"footway": "sidewalk", "highway": "footway", "kerb": "raised"}}, {"type": "way", "id": 1217769084, "tags": {"footway": "sidewalk", "highway": "footway", "kerb": "raised"}}, {"type": "way", "id": 1217769085, "tags": {"highway": "footway"}}, {"type": "way", "id": 1217769086, "tags": {"footway": "sidewalk", "highway": "footway", "kerb": "raised"}}, {"type": "way", "id": 1217769087, "tags": {"footway": "sidewalk", "highway": "footway", "kerb": "raised"}}, {"type": "way", "id": 1217769088, "tags": {"footway": "sidewalk", "highway": "footway", "kerb": "raised"}}, {"type": "way", "id": 1217769090, "tags": {"footway": "sidewalk", "highway": "footway"}}, {"type": "way", "id": 1262134169, "tags": {"access": "private", "highway": "service"}}, {"type": "way", "id": 1301131710, "tags": {"footway": "sidewalk", "highway": "footway", "lit": "yes", "smoothness": "excellent", "surface": "paving_stones"}}, {"type": "way", "id": 1304119371, "tags": {"footway": "sidewalk", "highway": "footway", "smoothness": "excellent", "surface": "paving_stones"}}, {"type": "way", "id": 1305050523, "tags": {"access": "permissive", "construction": "service", "highway": "construction"}}, {"type": "way", "id": 1305050529, "tags": {"access": "permissive", "construction": "service", "highway": "construction", "incline": "yes"}}, {"type": "way", "id": 1305050530, "tags": {"access": "permissive", "construction": "service", "highway": "construction"}}, {"type": "way", "id": 1306874868, "tags": {"footway": "sidewalk", "highway": "footway"}}, {"type": "way", "id": 1306874869, "tags": {"crossing": "uncontrolled", "crossing:markings": "zebra", "footway": "crossing", "highway": "footway", "surface": "asphalt"}}, {"type": "way", "id": 1307397842, "tags": {"hazard": "school_zone", "highway": "secondary", "lanes": "2", "name": "Museum Road", "name:kn": "\u0cb8\u0c82\u0c97\u0ccd\u0cb0\u0cb9\u0cbe\u0cb2\u0caf \u0cb0\u0cb8\u0ccd\u0ca4\u0cc6", "oneway": "yes", "sidewalk": "separate", "smoothness": "excellent", "surface": "asphalt"}}, {"type": "way", "id": 1307949916, "tags": {"area": "yes", "highway": "pedestrian"}}, {"type": "way", "id": 1308943983, "tags": {"highway": "service", "service": "driveway"}}, {"type": "way", "id": 1308943984, "tags": {"crossing": "uncontrolled", "crossing:markings": "zebra", "footway": "crossing", "highway": "footway", "surface": "asphalt"}}, {"type": "way", "id": 1311151870, "tags": {"access": "permissive", "highway": "service", "service": "driveway"}}, {"type": "way", "id": 1347087399, "tags": {"footway": "sidewalk", "highway": "footway", "smoothness": "good", "surface": "paving_stones"}}, {"type": "way", "id": 1347087403, "tags": {"footway": "sidewalk", "highway": "footway", "smoothness": "good", "surface": "paving_stones"}}, {"type": "way", "id": 1347087405, "tags": {"footway": "sidewalk", "highway": "footway", "smoothness": "good", "surface": "paving_stones"}}, {"type": "way", "id": 1347087406, "tags": {"crossing": "unmarked", "crossing:island": "no", "crossing:markings": "no", "footway": "crossing", "highway": "footway", "surface": "asphalt", "tactile_paving": "no"}}, {"type": "way", "id": 1353666162, "tags": {"access": "private", "highway": "service", "oneway": "yes", "service": "driveway"}}, {"type": "way", "id": 1466165195, "tags": {"footway": "sidewalk", "highway": "footway", "smoothness": "excellent", "surface": "stone", "tactile_paving": "yes"}}, {"type": "way", "id": 1466165196, "tags": {"crossing": "uncontrolled", "footway": "crossing", "highway": "footway"}}, {"type": "way", "id": 1466165197, "tags": {"footway": "sidewalk", "highway": "footway"}}, {"type": "way", "id": 1466165198, "tags": {"access": "no", "comment": "Temporarily closed for white topping works", "highway": "tertiary", "lane_markings": "no", "name": "Magrath Road", "name:kn": "\u0cae\u0c97\u0ccd\u0cb0\u0cbe\u0ca4\u0ccd \u0cb0\u0cb8\u0ccd\u0ca4\u0cc6", "oneway": "no", "smoothness": "excellent", "surface": "asphalt"}}, {"type": "way", "id": 1468136072, "tags": {"area": "yes", "highway": "footway", "surface": "paving_stones"}}, {"type": "way", "id": 1468136081, "tags": {"footway": "sidewalk", "highway": "footway", "surface": "paving_stones"}}, {"type": "way", "id": 1468136082, "tags": {"footway": "sidewalk", "highway": "footway", "surface": "paving_stones"}}, {"type": "way", "id": 1468136083, "tags": {"crossing": "uncontrolled", "footway": "crossing", "highway": "footway", "surface": "asphalt"}}]}